mn_translit/__init__.py
mn_translit/translit.py
mn_translit-1.0.0.dist-info/licenses/LICENSE
mn_translit-1.0.0.dist-info/METADATA
mn_translit-1.0.0.dist-info/WHEEL
mn_translit-1.0.0.dist-info/top_level.txt
mn_translit-1.0.0.dist-info/RECORD
