Metadata-Version: 2.4
Name: mn-translit
Version: 1.0.0
Summary: Mongolian Latin-Cyrillic transliteration library following MNS 5217:2012 standard
Author-email: Battseren Badral <bbattseren88@gmail.com>
License: MIT
Project-URL: Homepage, https://github.com/btseee/mn-translit
Project-URL: Bug Reports, https://github.com/btseee/mn-translit/issues
Project-URL: Source, https://github.com/btseee/mn-translit
Keywords: mongolian,transliteration,cyrillic,latin,mns-5217
Classifier: Development Status :: 4 - Beta
Classifier: Intended Audience :: Developers
Classifier: Topic :: Text Processing :: Linguistic
Classifier: License :: OSI Approved :: MIT License
Classifier: Programming Language :: Python :: 2
Classifier: Programming Language :: Python :: 2.7
Classifier: Programming Language :: Python :: 3
Classifier: Programming Language :: Python :: 3.4
Classifier: Programming Language :: Python :: 3.5
Classifier: Programming Language :: Python :: 3.6
Classifier: Programming Language :: Python :: 3.7
Classifier: Programming Language :: Python :: 3.8
Classifier: Programming Language :: Python :: 3.9
Classifier: Programming Language :: Python :: 3.10
Classifier: Programming Language :: Python :: 3.11
Classifier: Programming Language :: Python :: 3.12
Requires-Python: !=3.0.*,!=3.1.*,!=3.2.*,!=3.3.*,>=2.7
License-File: LICENSE
Dynamic: license-file
